{
  "manifest": {
    "apis": {
      "custom": {
        "endpoint": {
          "uri": "arn:aws:lambda:us-east-1:628986087069:function:6f16adaf-d549-4748-a8d5-895ab2d077da:Release_0"
        },
        "interfaces": [
          {
            "minimumTemplateVersion": "1.0",
            "type": "RENDER_TEMPLATE"
          }
        ],
        "regions": {
          "EU": {
            "endpoint": {
              "uri": "arn:aws:lambda:eu-west-1:628986087069:function:6f16adaf-d549-4748-a8d5-895ab2d077da:Release_0"
            }
          },
          "NA": {
            "endpoint": {
              "uri": "arn:aws:lambda:us-east-1:628986087069:function:6f16adaf-d549-4748-a8d5-895ab2d077da:Release_0"
            }
          },
          "FE": {
            "endpoint": {
              "uri": "arn:aws:lambda:us-west-2:628986087069:function:6f16adaf-d549-4748-a8d5-895ab2d077da:Release_0"
            }
          }
        }
      }
    },
    "manifestVersion": "1.0",
    "publishingInformation": {
      "category": "KNOWLEDGE_AND_TRIVIA",
      "distributionCountries": [],
      "isAvailableWorldwide": true,
      "locales": {
        "en-US": {
          "description": "Sample Full Description",
          "examplePhrases": [
            "Alexa open hello world",
            "hello",
            "help"
          ],
          "keywords": [],
          "name": "greeter",
          "summary": "Sample Short Description"
        }
      },
      "testingInstructions": "Sample Testing Instructions."
    }
  }
}